streamlit_shortcuts.py
streamlit_shortcuts-1.2.1.dist-info/METADATA
streamlit_shortcuts-1.2.1.dist-info/WHEEL
streamlit_shortcuts-1.2.1.dist-info/licenses/LICENSE
streamlit_shortcuts-1.2.1.dist-info/RECORD
