Metadata-Version: 2.4
Name: streamlit-shortcuts
Version: 1.2.1
Summary: Streamlit keyboard shortcuts for your buttons.
Project-URL: Repository, https://github.com/adriangalilea/streamlit-shortcuts
Author-email: Adrian Galilea Delgado <adriangalilea@gmail.com>
License: MIT
License-File: LICENSE
Classifier: Programming Language :: Python :: 3
Classifier: Programming Language :: Python :: 3.9
Classifier: Programming Language :: Python :: 3.10
Classifier: Programming Language :: Python :: 3.11
Classifier: Programming Language :: Python :: 3.12
Requires-Python: >=3.9
Requires-Dist: streamlit>=1.45.0
